GPy.libs/libgomp-a34b3233.so.1.0.0
GPy-1.13.2.dist-info/WHEEL
GPy-1.13.2.dist-info/top_level.txt
GPy-1.13.2.dist-info/AUTHORS.txt
GPy-1.13.2.dist-info/RECORD
GPy-1.13.2.dist-info/METADATA
GPy-1.13.2.dist-info/LICENSE.txt
GPy/__init__.py
GPy/defaults.cfg
GPy/installation.cfg
GPy/__version__.py
GPy/models/sparse_gp_minibatch.py
GPy/models/gp_multiout_regression.py
GPy/models/gplvm.py
GPy/models/tp_regression.py
GPy/models/state_space_cython.c
GPy/models/__init__.py
GPy/models/multioutput_gp.py
GPy/models/sparse_gp_classification.py
GPy/models/gp_heteroscedastic_regression.py
GPy/models/state_space_cython.cpython-311-x86_64-linux-gnu.so
GPy/models/sparse_gp_coregionalized_regression.py
GPy/models/input_warped_gp.py
GPy/models/mrd.py
GPy/models/ss_gplvm.py
GPy/models/sparse_gplvm.py
GPy/models/gp_regression.py
GPy/models/ss_mrd.py
GPy/models/state_space_main.py
GPy/models/state_space_model.py
GPy/models/gp_grid_regression.py
GPy/models/bayesian_gplvm.py
GPy/models/gradient_checker.py
GPy/models/gp_kronecker_gaussian_regression.py
GPy/models/ibp_lfm.py
GPy/models/gp_coregionalized_regression.py
GPy/models/bcgplvm.py
GPy/models/one_vs_all_classification.py
GPy/models/gp_multiout_regression_md.py
GPy/models/sparse_gp_regression_md.py
GPy/models/dpgplvm.py
GPy/models/one_vs_all_sparse_classification.py
GPy/models/warped_gp.py
GPy/models/state_space.py
GPy/models/state_space_cython.pyx
GPy/models/gp_offset_regression.py
GPy/models/gp_classification.py
GPy/models/sparse_gp_regression.py
GPy/models/bayesian_gplvm_minibatch.py
GPy/models/state_space_setup.py
GPy/models/gp_var_gauss.py
GPy/util/mocap.py
GPy/util/parallel.py
GPy/util/choleskies.py
GPy/util/__init__.py
GPy/util/block_matrices.py
GPy/util/linalg_gpu.py
GPy/util/linalg_cython.pyx
GPy/util/debug.py
GPy/util/ln_diff_erfs.py
GPy/util/input_warping_functions.py
GPy/util/squashers.py
GPy/util/subarray_and_sorting.py
GPy/util/linalg_cython.cpython-311-x86_64-linux-gnu.so
GPy/util/quad_integrate.py
GPy/util/functions.py
GPy/util/decorators.py
GPy/util/choleskies_cython.pyx
GPy/util/choleskies_cython.cpython-311-x86_64-linux-gnu.so
