Metadata-Version: 2.1
Name: GPy
Version: 1.13.2
Summary: The Gaussian Process Toolbox
Home-page: https://sheffieldml.github.io/GPy/
Author: GPy Authors: https://github.com/SheffieldML/GPy/graphs/contributors
Author-email: gpy.authors@gmail.com
License: BSD 3-clause
Download-URL: https://github.com/SheffieldML/GPy/archive/refs/heads/devel.zip
Project-URL: Source Code, https://github.com/SheffieldML/GPy
Project-URL: Bug Tracker, https://github.com/SheffieldML/GPy/issues
Keywords: machine-learning gaussian-processes kernels
Platform: UNKNOWN
Classifier: License :: OSI Approved :: BSD License
Classifier: Natural Language :: English
Classifier: Operating System :: MacOS :: MacOS X
Classifier: Operating System :: Microsoft :: Windows
Classifier: Operating System :: POSIX :: Linux
Classifier: Programming Language :: Python :: 3.5
Classifier: Programming Language :: Python :: 3.6
Classifier: Programming Language :: Python :: 3.7
Classifier: Programming Language :: Python :: 3.8
Classifier: Programming Language :: Python :: 3.9
Classifier: Framework :: IPython
Classifier: Intended Audience :: Science/Research
Classifier: Intended Audience :: Developers
Classifier: Topic :: Software Development
Classifier: Topic :: Software Development :: Libraries :: Python Modules
Requires-Python: >=3.9
Provides-Extra: docs
Provides-Extra: optional
Provides-Extra: plotting
Provides-Extra: notebook
Provides-Extra: dev
License-File: LICENSE.txt
License-File: AUTHORS.txt
